version_tracker/__init__.py
version_tracker/cli.py
version_tracker/version_tracker.py
version_tracker-0.2.1.dist-info/AUTHORS.rst
version_tracker-0.2.1.dist-info/LICENSE
version_tracker-0.2.1.dist-info/METADATA
version_tracker-0.2.1.dist-info/WHEEL
version_tracker-0.2.1.dist-info/entry_points.txt
version_tracker-0.2.1.dist-info/top_level.txt
version_tracker-0.2.1.dist-info/RECORD
