Metadata-Version: 2.1
Name: version-tracker
Version: 0.2.1
Summary: Query PyPI for critical updates available available for your users installation of your package.
Home-page: https://github.com/prabhakk-mw/version_tracker
Author: Prabhakar Kumar
Author-email: prabhakk@mathworks.com
License: MIT license
Keywords: version_tracker
Platform: UNKNOWN
Classifier: Development Status :: 2 - Pre-Alpha
Classifier: Intended Audience :: Developers
Classifier: License :: OSI Approved :: MIT License
Classifier: Natural Language :: English
Classifier: Programming Language :: Python :: 3
Classifier: Programming Language :: Python :: 3.6
Classifier: Programming Language :: Python :: 3.7
Classifier: Programming Language :: Python :: 3.8
Requires-Python: >=3.6
Requires-Dist: requests
